audire/__init__.py
audire/dotdict.py
audire/errors.py
audire/main.py
audire/helpers/__init__.py
audire/helpers/saavn.py
audire/helpers/soundcloud.py
audire/helpers/spotify.py
audire/helpers/youtube.py
Audire-1.1.0.dist-info/LICENSE
Audire-1.1.0.dist-info/METADATA
Audire-1.1.0.dist-info/WHEEL
Audire-1.1.0.dist-info/top_level.txt
Audire-1.1.0.dist-info/RECORD
