Metadata-Version: 2.1
Name: Audire
Version: 1.1.0
Summary: A Package to search and get download links for songs from various platforms asynchronously.
Home-page: https://github.com/LinuxGuy312/Audire
Author: Eren
Author-email: linuxguy312@segfault.net
License: MIT
Keywords: songs,song,music,youtube,ytm,Audire,audire
Classifier: Programming Language :: Python :: 3
Classifier: Programming Language :: Python :: 3.7
Classifier: Programming Language :: Python :: 3.8
Classifier: Programming Language :: Python :: 3.9
Classifier: Programming Language :: Python :: 3.10
Classifier: Programming Language :: Python :: 3.11
Classifier: Development Status :: 5 - Production/Stable
Classifier: License :: OSI Approved :: MIT License
Requires-Python: ~=3.7
License-File: LICENSE
Requires-Dist: aiohttp
Requires-Dist: bs4
